POS-Tabla-4/tabla04POS_tb.v
module tabla04POS();

	reg A, B, C, D;
	wire w1, w2, w3, w4, out, w5, w6, w7, w8,w9, w10, w11, w12, w13;
	
	not N1(w1, A);
	not N2(w2, B);
	not N3(w3, C);
	not N4(w4, D);
	or O1(w5, A, B, C, w4);
	or O2(w6, A, w2, C, D);
	or O3(w7, A, w2, C, w4);
	or O4(w8, w1, B, C, w4);
	or O5(w9, w1, B, w3, D);
	or O6(w10, w1, w2, C, w4);
	or O7(w11, w1, w2, w3, D);
	or O8(w12, w1, w2, w3, w4);
	or O9(w13, w1, B, w3, w4);
	and A1(out, w5, w6, w7, w8,w9, w10, w11, w12, w13);
	
	initial begin
		$display("A B C D| Y");
		$display("---------");
		$monitor("%b %b %b %b| %b", A, B, C, D, out);
		A=0; B=0; C=0; D=0;
		#1 D=1;
		#1 D=0; C=1;
		#1 D=1;
		#1 D=0; B=1;
		#1 D=1;
		#1 D=0; C=1;
		#1 D=1; 
		#1 D=0; B=0; C=0; A=1;
		#1 D=1;
		#1 D=0; C=1;
		#1 D=1;
		#1 D=0; B=1; C=0;
		#1 D=1;
		#1 D=0; C=1;
		#1 D=1;
		
	end 
	
	initial
		begin
			$dumpfile("tabla04POS.vcd");
			$dumpvars(0, tabla04POS);
		
		end	


endmodule

POS-Tabla-4/tabla04POS.vcd
$date
	Fri Jul 31 19:46:09 2020
$end
$version
	Icarus Verilog
$end
$timescale
	1ps
$end
$scope module tabla04POS $end
$var wire 1 ! out $end
$var wire 1 " w1 $end
$var wire 1 # w10 $end
$var wire 1 $ w11 $end
$var wire 1 % w12 $end
$var wire 1 & w13 $end
$var wire 1 ' w2 $end
$var wire 1 ( w3 $end
$var wire 1 ) w4 $end
$var wire 1 * w5 $end
$var wire 1 + w6 $end
$var wire 1 , w7 $end
$var wire 1 - w8 $end
$var wire 1 . w9 $end
$var reg 1 / A $end
$var reg 1 0 B $end
$var reg 1 1 C $end
$var reg 1 2 D $end
$upscope $end
$enddefinitions $end
#0
$dumpvars
02
01
00
0/
1.
1-
1,
1+
1*
1)
1(
1'
1&
1%
1$
1#
1"
1!
$end
#1
0!
0*
0)
12
#2
1!
1*
0(
1)
11
02
#3
0)
12
#4
0'
1)
10
02
#5
0)
12
#6
1)
02
#7
0)
12
#8
0"
1(
1'
1)
1/
01
00
02
#9
0!
0-
0)
12
#10
0.
1-
0(
1)
11
02
#11
0&
1.
0)
12
#12
1!
1(
1&
0'
1)
01
10
02
#13
0!
0#
0)
12
#14
0$
1#
0(
1)
11
02
#15
0%
1$
0)
12
