POS-Tabla-2/tabla02POS_tb.v
module tabla02POS();
	
	reg A, B, C;
	wire w1, w2, w3, w4, w5, w6, w7, w8, out;
	
	not N1(w1, A);
	not N2(w2, B);
	not N3(w3, C);
	or O1(w4, A, B, C);
	or O2(w5, A, w2, C);
	or O3(w6, A, w2, w3);
	or O4(w7, w1, B, C);
	or O5(w8, w1, B, w3);
	and (out, w4, w5,w6, w7, w8);
	
	initial begin
		$display("A B C | Y");
		$display("---------");
		$monitor("%b %b %b | %b", A, B, C, out);
		A=0; B=0; C=0;
		#1 C=1;
		#1 B=1; C=0;
		#1 C=1;
		#1 A=1; B=0; C=0;
		#1 C=1;
		#1 C=0; B=1;
		#1 C=1; A=1;
		#1 $finish;
		
	end 
	
initial
		begin
			$dumpfile("tabla02POS.vcd");
			$dumpvars(0, tabla02POS);
		
		end	
		



endmodule

POS-Tabla-2/tabla02POS.vcd
$date
	Fri Jul 31 18:38:40 2020
$end
$version
	Icarus Verilog
$end
$timescale
	1ps
$end
$scope module tabla02POS $end
$var wire 1 ! out $end
$var wire 1 " w1 $end
$var wire 1 # w2 $end
$var wire 1 $ w3 $end
$var wire 1 % w4 $end
$var wire 1 & w5 $end
$var wire 1 ' w6 $end
$var wire 1 ( w7 $end
$var wire 1 ) w8 $end
$var reg 1 * A $end
$var reg 1 + B $end
$var reg 1 , C $end
$upscope $end
$enddefinitions $end
#0
$dumpvars
0,
0+
0*
1)
1(
1'
1&
0%
1$
1#
1"
0!
$end
#1
1!
1%
0$
1,
#2
0!
0&
1$
0#
0,
1+
#3
0'
1&
0$
1,
#4
1$
1)
0(
1#
1'
0"
0,
0+
1*
#5
0)
1(
0$
1,
#6
1!
1)
0#
1$
1+
0,
#7
0$
1,
