SOP-Tabla-2/tabla02SOP_tb.v
module tabla02SOP();

	reg A, B, C;
	wire w1, w2, w3, w4, w5, w6, out;

	not N1(w1, A);
	not N2(w2, B);
	not N3(w3, C);
	and A1(w4, w1, w2, C);
	and A2(w5, A, B, w3);
	and A3(w6, A, B, C);
	or O1(out, w4, w5, w6);
	
	initial begin
		$display("A B C | Y");
		$display("---------");
		$monitor("%b %b %b | %b", A, B, C, out);
		A=0; B=0; C=0;
		#1 C=1;
		#1 B=1; C=0;
		#1 C=1;
		#1 A=1; B=0; C=0;
		#1 C=1;
		#1 C=0; B=1;
		#1 C=1; A=1;
		#1 $finish;
		
	end 
	
initial
		begin
			$dumpfile("tabla02SOP.vcd");
			$dumpvars(0, tabla02SOP);
		
		end	

endmodule

SOP-Tabla-2/tabla02SOP.vcd
$date
	Fri Jul 31 18:46:35 2020
$end
$version
	Icarus Verilog
$end
$timescale
	1ps
$end
$scope module tabla02SOP $end
$var wire 1 ! out $end
$var wire 1 " w1 $end
$var wire 1 # w2 $end
$var wire 1 $ w3 $end
$var wire 1 % w4 $end
$var wire 1 & w5 $end
$var wire 1 ' w6 $end
$var reg 1 ( A $end
$var reg 1 ) B $end
$var reg 1 * C $end
$upscope $end
$enddefinitions $end
#0
$dumpvars
0*
0)
0(
0'
0&
0%
1$
1#
1"
0!
$end
#1
1!
1%
0$
1*
#2
0!
0%
1$
0#
0*
1)
#3
0$
1*
#4
1$
1#
0"
0*
0)
1(
#5
0$
1*
#6
1!
1&
0#
1$
1)
0*
#7
0&
1'
0$
1*
