SOP-Tabla-3/tabla03SOP_tb.v
module tabla03SOP();

	reg A, B, C, D;
	wire w1, w2, w3, w4, w5, w6, w7, w8, w9, w10, w11, out;
	
	not N1(w1, A);
	not N2(w2, B);
	not N3(w3, C);
	not N4(w4, D);
	and A1(w5, w1, w2, w3, w4);
	and A2(w6, w1, w2, w3, D);
	and A3(w7, w1, w2, C, w4);
	and A4(w8, w1, w2, C, D);
	and A5(w9, A, w2, w3, w4);
	and A6(w10, A, w2, C, w4);
	and A7(w11, A, B, C, w4);
	or O1(out, w5, w6, w7, w8, w9, w10, w11);
	
	initial begin
		$display("A B C D| Y");
		$display("---------");
		$monitor("%b %b %b %b| %b", A, B, C, D, out);
		A=0; B=0; C=0; D=0;
		#1 D=1;
		#1 D=0; C=1;
		#1 D=1;
		#1 D=0; B=1;
		#1 D=1;
		#1 D=0; C=1;
		#1 D=1; 
		#1 D=0; B=0; C=0; A=1;
		#1 D=1;
		#1 D=0; C=1;
		#1 D=1;
		#1 D=0; B=1; C=0;
		#1 D=1;
		#1 D=0; C=1;
		#1 D=1;
		
	end 
	
	initial
		begin
			$dumpfile("tabla03SOP.vcd");
			$dumpvars(0, tabla03SOP);
		
		end	


endmodule

SOP-Tabla-3/tabla03SOP.vcd
$date
	Fri Jul 31 19:12:21 2020
$end
$version
	Icarus Verilog
$end
$timescale
	1ps
$end
$scope module tabla03SOP $end
$var wire 1 ! out $end
$var wire 1 " w1 $end
$var wire 1 # w10 $end
$var wire 1 $ w11 $end
$var wire 1 % w2 $end
$var wire 1 & w3 $end
$var wire 1 ' w4 $end
$var wire 1 ( w5 $end
$var wire 1 ) w6 $end
$var wire 1 * w7 $end
$var wire 1 + w8 $end
$var wire 1 , w9 $end
$var reg 1 - A $end
$var reg 1 . B $end
$var reg 1 / C $end
$var reg 1 0 D $end
$upscope $end
$enddefinitions $end
#0
$dumpvars
00
0/
0.
0-
0,
0+
0*
0)
1(
1'
1&
1%
0$
0#
1"
1!
$end
#1
0(
1)
0'
10
#2
1*
0&
0)
1'
1/
00
#3
0*
1+
0'
10
#4
0!
0%
0+
1'
1.
00
#5
0'
10
#6
1'
00
#7
0'
10
#8
1!
1,
0"
1&
1%
1'
1-
0/
0.
00
#9
0!
0,
0'
10
#10
1!
1#
0&
1'
1/
00
#11
0!
0#
0'
10
#12
1&
0%
1'
0/
1.
00
#13
0'
10
#14
1!
1$
0&
1'
1/
00
#15
0!
0$
0'
10
